ncode/ncode.py
ncode-0.0.1.dist-info/METADATA
ncode-0.0.1.dist-info/WHEEL
ncode-0.0.1.dist-info/top_level.txt
ncode-0.0.1.dist-info/RECORD
