Metadata-Version: 2.1
Name: ncode
Version: 0.0.1
Summary: NomanCode E-Dcoder
Home-page: UNKNOWN
Author: sooyey
Author-email: sooyooshung@gmail.com
License: MIT
Platform: UNKNOWN
Requires-Python: >=3
